pytedee/Lock.py
pytedee/TedeeClient.py
pytedee/TedeeClientException.py
pytedee/__init__.py
pytedee/example.py
pytedee-0.0.3.dist-info/LICENSE
pytedee-0.0.3.dist-info/METADATA
pytedee-0.0.3.dist-info/WHEEL
pytedee-0.0.3.dist-info/top_level.txt
pytedee-0.0.3.dist-info/RECORD
