Metadata-Version: 2.1
Name: pytedee
Version: 0.0.3
Summary: A Tedee Lock Client package
Home-page: https://github.com/joerg65/pytedee
Author: Jörg Wolff
Author-email: joerg.wolff@gmx.de
License: UNKNOWN
Platform: UNKNOWN
Classifier: Programming Language :: Python :: 3
Classifier: License :: OSI Approved :: MIT License
Classifier: Operating System :: OS Independent
Requires-Python: >=3.6
Requires-Dist: requests
